{
"meta":{"test_sets":[],"test_metrics":[],"learn_metrics":[{"best_value":"Min","name":"RMSE"}],"launch_mode":"Train","parameters":"","iteration_count":100,"learn_sets":["learn"],"name":"experiment"},
"iterations":[
{"learn":[14.005006],"iteration":0,"passed_time":0.001466924106,"remaining_time":0.1452254865},
{"learn":[13.14441192],"iteration":1,"passed_time":0.002740037942,"remaining_time":0.1342618591},
{"learn":[12.34258257],"iteration":2,"passed_time":0.004164875434,"remaining_time":0.1346643057},
{"learn":[11.64527793],"iteration":3,"passed_time":0.005011277027,"remaining_time":0.1202706487},
{"learn":[11.02766183],"iteration":4,"passed_time":0.006348778897,"remaining_time":0.120626799},
{"learn":[10.43485794],"iteration":5,"passed_time":0.007737503097,"remaining_time":0.1212208819},
{"learn":[9.890641275],"iteration":6,"passed_time":0.008856771593,"remaining_time":0.1176685369},
{"learn":[9.492161212],"iteration":7,"passed_time":0.01010353711,"remaining_time":0.1161906768},
{"learn":[9.105082953],"iteration":8,"passed_time":0.01128962975,"remaining_time":0.1141507008},
{"learn":[8.674157135],"iteration":9,"passed_time":0.01239764045,"remaining_time":0.111578764},
{"learn":[8.341743544],"iteration":10,"passed_time":0.01346300452,"remaining_time":0.1089279456},
{"learn":[8.049372916],"iteration":11,"passed_time":0.01455329614,"remaining_time":0.1067241717},
{"learn":[7.757318612],"iteration":12,"passed_time":0.01564978211,"remaining_time":0.1047331572},
{"learn":[7.522206899],"iteration":13,"passed_time":0.01679408163,"remaining_time":0.1031636443},
{"learn":[7.297756655],"iteration":14,"passed_time":0.01791792725,"remaining_time":0.1015349211},
{"learn":[7.088359431],"iteration":15,"passed_time":0.01905015532,"remaining_time":0.1000133154},
{"learn":[6.882113791],"iteration":16,"passed_time":0.02004723503,"remaining_time":0.09787767689},
{"learn":[6.704728832],"iteration":17,"passed_time":0.02102179309,"remaining_time":0.09576594631},
{"learn":[6.563881962],"iteration":18,"passed_time":0.0222521202,"remaining_time":0.0948643019},
{"learn":[6.418790279],"iteration":19,"passed_time":0.02327212133,"remaining_time":0.0930884853},
{"learn":[6.315756953],"iteration":20,"passed_time":0.02413625165,"remaining_time":0.09079828002},
{"learn":[6.210157751],"iteration":21,"passed_time":0.02510766021,"remaining_time":0.08901806801},
{"learn":[6.115058449],"iteration":22,"passed_time":0.02607253986,"remaining_time":0.08728632909},
{"learn":[6.014819884],"iteration":23,"passed_time":0.02709648562,"remaining_time":0.08580553781},
{"learn":[5.93117229],"iteration":24,"passed_time":0.02815030685,"remaining_time":0.08445092056},
{"learn":[5.844857622],"iteration":25,"passed_time":0.02916044075,"remaining_time":0.08299510059},
{"learn":[5.771145213],"iteration":26,"passed_time":0.03017594044,"remaining_time":0.08158680194},
{"learn":[5.704018229],"iteration":27,"passed_time":0.03109491204,"remaining_time":0.07995834524},
{"learn":[5.665806474],"iteration":28,"passed_time":0.03204742111,"remaining_time":0.07846092755},
{"learn":[5.616500369],"iteration":29,"passed_time":0.03302087083,"remaining_time":0.07704869861},
{"learn":[5.558023666],"iteration":30,"passed_time":0.03394609998,"remaining_time":0.07555744834},
{"learn":[5.510080976],"iteration":31,"passed_time":0.03484523525,"remaining_time":0.0740461249},
{"learn":[5.468747792],"iteration":32,"passed_time":0.03575014939,"remaining_time":0.07258363663},
{"learn":[5.429275534],"iteration":33,"passed_time":0.03663170207,"remaining_time":0.07110859813},
{"learn":[5.402117324],"iteration":34,"passed_time":0.03752895439,"remaining_time":0.06969662959},
{"learn":[5.367635151],"iteration":35,"passed_time":0.03831171356,"remaining_time":0.068109713},
{"learn":[5.345181232],"iteration":36,"passed_time":0.03935605002,"remaining_time":0.06701165275},
{"learn":[5.319151269],"iteration":37,"passed_time":0.04035303512,"remaining_time":0.06583916257},
{"learn":[5.296134146],"iteration":38,"passed_time":0.04129726843,"remaining_time":0.06459316344},
{"learn":[5.269629003],"iteration":39,"passed_time":0.04223296347,"remaining_time":0.0633494452},
{"learn":[5.251147059],"iteration":40,"passed_time":0.04320946728,"remaining_time":0.06217947731},
{"learn":[5.248003302],"iteration":41,"passed_time":0.04358396077,"remaining_time":0.0601873744},
{"learn":[5.232376509],"iteration":42,"passed_time":0.044530571,"remaining_time":0.05902889645},
{"learn":[5.213524255],"iteration":43,"passed_time":0.04553786498,"remaining_time":0.0579572827},
{"learn":[5.189691584],"iteration":44,"passed_time":0.0464670126,"remaining_time":0.0567930154},
{"learn":[5.166052198],"iteration":45,"passed_time":0.04738243088,"remaining_time":0.05562285364},
{"learn":[5.140406659],"iteration":46,"passed_time":0.04831827649,"remaining_time":0.05448656711},
{"learn":[5.118929684],"iteration":47,"passed_time":0.04935311772,"remaining_time":0.05346587753},
{"learn":[5.108792602],"iteration":48,"passed_time":0.05046409595,"remaining_time":0.05252385497},
{"learn":[5.098141225],"iteration":49,"passed_time":0.05143410991,"remaining_time":0.05143410991},
{"learn":[5.085926393],"iteration":50,"passed_time":0.05250329221,"remaining_time":0.05044433957},
{"learn":[5.067816804],"iteration":51,"passed_time":0.05338517582,"remaining_time":0.04927862384},
{"learn":[5.049834901],"iteration":52,"passed_time":0.05437133511,"remaining_time":0.04821608962},
{"learn":[5.03838627],"iteration":53,"passed_time":0.05548549023,"remaining_time":0.0472654176},
{"learn":[5.033534248],"iteration":54,"passed_time":0.05600056189,"remaining_time":0.04581864155},
{"learn":[5.023726885],"iteration":55,"passed_time":0.05690315305,"remaining_time":0.04470962025},
{"learn":[5.01290392],"iteration":56,"passed_time":0.05796855738,"remaining_time":0.04373066609},
{"learn":[5.005569127],"iteration":57,"passed_time":0.05894728111,"remaining_time":0.04268596218},
{"learn":[4.989969032],"iteration":58,"passed_time":0.05998993391,"remaining_time":0.04168792018},
{"learn":[4.976762446],"iteration":59,"passed_time":0.06091426205,"remaining_time":0.04060950803},
{"learn":[4.967222715],"iteration":60,"passed_time":0.06190443925,"remaining_time":0.03957824804},
{"learn":[4.954407599],"iteration":61,"passed_time":0.06292596823,"remaining_time":0.03856752891},
{"learn":[4.942125056],"iteration":62,"passed_time":0.06391880054,"remaining_time":0.03753961302},
{"learn":[4.930230716],"iteration":63,"passed_time":0.06496187849,"remaining_time":0.03654105665},
{"learn":[4.921695642],"iteration":64,"passed_time":0.06595371599,"remaining_time":0.03551353938},
{"learn":[4.906405625],"iteration":65,"passed_time":0.06694922799,"remaining_time":0.03448899624},
{"learn":[4.894330248],"iteration":66,"passed_time":0.06786962236,"remaining_time":0.03342832146},
{"learn":[4.88211557],"iteration":67,"passed_time":0.06879405074,"remaining_time":0.03237367094},
{"learn":[4.877946398],"iteration":68,"passed_time":0.0697499839,"remaining_time":0.03133694929},
{"learn":[4.863182126],"iteration":69,"passed_time":0.07076928692,"remaining_time":0.03032969439},
{"learn":[4.84646533],"iteration":70,"passed_time":0.07185314546,"remaining_time":0.02934846786},
{"learn":[4.838014752],"iteration":71,"passed_time":0.07281257959,"remaining_time":0.02831600318},
{"learn":[4.82981137],"iteration":72,"passed_time":0.07385685486,"remaining_time":0.02731691892},
{"learn":[4.817094767],"iteration":73,"passed_time":0.07487816201,"remaining_time":0.02630854341},
{"learn":[4.808314151],"iteration":74,"passed_time":0.07587918837,"remaining_time":0.02529306279},
{"learn":[4.796235023],"iteration":75,"passed_time":0.07681526467,"remaining_time":0.024257452},
{"learn":[4.784434534],"iteration":76,"passed_time":0.07775794033,"remaining_time":0.02322639776},
{"learn":[4.774402487],"iteration":77,"passed_time":0.07868109369,"remaining_time":0.02219210335},
{"learn":[4.76731896],"iteration":78,"passed_time":0.07949642008,"remaining_time":0.02113195977},
{"learn":[4.75934113],"iteration":79,"passed_time":0.08040411536,"remaining_time":0.02010102884},
{"learn":[4.754106378],"iteration":80,"passed_time":0.08126844859,"remaining_time":0.01906296942},
{"learn":[4.744002932],"iteration":81,"passed_time":0.08224685185,"remaining_time":0.01805418699},
{"learn":[4.731700554],"iteration":82,"passed_time":0.08330580981,"remaining_time":0.01706263574},
{"learn":[4.723284153],"iteration":83,"passed_time":0.08440210495,"remaining_time":0.01607659142},
{"learn":[4.712232782],"iteration":84,"passed_time":0.08536280082,"remaining_time":0.01506402367},
{"learn":[4.703046867],"iteration":85,"passed_time":0.08627255417,"remaining_time":0.01404436928},
{"learn":[4.698601855],"iteration":86,"passed_time":0.08728257775,"remaining_time":0.01304222426},
{"learn":[4.692429407],"iteration":87,"passed_time":0.0881825315,"remaining_time":0.01202489066},
{"learn":[4.675027364],"iteration":88,"passed_time":0.08906907758,"remaining_time":0.01100853768},
{"learn":[4.662368584],"iteration":89,"passed_time":0.09001367685,"remaining_time":0.01000151965},
{"learn":[4.646206172],"iteration":90,"passed_time":0.09100212006,"remaining_time":0.009000209676},
{"learn":[4.641245848],"iteration":91,"passed_time":0.09207901328,"remaining_time":0.00800687072},
{"learn":[4.633900435],"iteration":92,"passed_time":0.09321349146,"remaining_time":0.00701606925},
{"learn":[4.624738236],"iteration":93,"passed_time":0.09420201117,"remaining_time":0.00601289433},
{"learn":[4.612798287],"iteration":94,"passed_time":0.09513607811,"remaining_time":0.005007162006},
{"learn":[4.605222001],"iteration":95,"passed_time":0.09612737452,"remaining_time":0.004005307272},
{"learn":[4.601725912],"iteration":96,"passed_time":0.09706923734,"remaining_time":0.003002141361},
{"learn":[4.59722371],"iteration":97,"passed_time":0.0980193252,"remaining_time":0.002000394392},
{"learn":[4.580235665],"iteration":98,"passed_time":0.09892704825,"remaining_time":0.0009992631136},
{"learn":[4.57591791],"iteration":99,"passed_time":0.09982809142,"remaining_time":0}
]}